parse_xsv/__init__.py
parse_xsv/__main__.py
parse_xsv/__version__.py
parse_xsv/cli/__init__.py
parse_xsv/cli/__main__.py
parse_xsv/cli/cli.py
parse_xsv/parse_xsv.py
parse_xsv/sample_gen/__init__.py
parse_xsv/sample_gen/__main__.py
parse_xsv/sample_gen/sample_gen.py
parse_xsv/showcase/__init__.py
parse_xsv/showcase/__main__.py
parse_xsv/showcase/corrupted_sample.csv
parse_xsv/showcase/sample.csv
parse_xsv/showcase/sample.tsv
parse_xsv/showcase/showcase.py
task3-1.0.5.dist-info/entry_points.txt
task3-1.0.5.dist-info/LICENSE
task3-1.0.5.dist-info/METADATA
task3-1.0.5.dist-info/WHEEL
task3-1.0.5.dist-info/RECORD
